costreport/__init__.py
costreport/main.py
aws_cost_report-0.0.6.dist-info/LICENSE
aws_cost_report-0.0.6.dist-info/METADATA
aws_cost_report-0.0.6.dist-info/WHEEL
aws_cost_report-0.0.6.dist-info/entry_points.txt
aws_cost_report-0.0.6.dist-info/top_level.txt
aws_cost_report-0.0.6.dist-info/RECORD
