Metadata-Version: 2.1
Name: aws-cost-report
Version: 0.0.6
Summary: command line tool which will return total cost for the current month's AWS usage.
Home-page: https://bitbucket.org/rednap/aws-cost-report-pypi
Author: Andy Klier
Author-email: andyklier@gmail.com
License: UNKNOWN
Platform: UNKNOWN
Classifier: Programming Language :: Python :: 3
Classifier: License :: OSI Approved :: MIT License
Classifier: Operating System :: OS Independent
Requires-Dist: python-dateutil
Requires-Dist: setuptools
